<?xml version="1.0" encoding="UTF-8"?>
<objects serializationModel="Studio.02.03.00">
	<object class="AudioFile" id="{c3e66625-04f1-4796-ab30-59e43d37b879}">
		<property name="assetPath">
			<value>MX_140BPM_Leilani.wav</value>
		</property>
		<property name="isStreaming">
			<value>true</value>
		</property>
		<property name="frequencyInKHz">
			<value>48</value>
		</property>
		<property name="channelCount">
			<value>2</value>
		</property>
		<property name="length">
			<value>13.714291666666666</value>
		</property>
		<relationship name="masterAssetFolder">
			<destination>{33fc172c-016a-4235-9242-e7ee3cd753a4}</destination>
		</relationship>
	</object>
</objects>
